{
    "homepage": "https://joytokey.net/",
    "license": "Shareware",
    "version": "6.8",
    "url": "https://joytokey.net/download/JoyToKey_en.zip",
    "hash": "d5d3fe0b8bf426dc6dcf7aa7f5c527619941d04a4706b99d80bf578a7e1ac53e",
    "shortcuts": [
        [
            "JoyToKey.exe",
            "JoyToKey"
        ]
    ],
    "checkver": {
        "url": "https://joytokey.net/en/news",
        "re": "JoyToKey ([\\d]+\\.[\\d]+)"
    },
    "autoupdate": {
        "url": "https://joytokey.net/download/JoyToKey_en.zip"
    }
}
